pvd/__init__.py
pvd/decorators.py
pvd/enforcer.py
pvd/sdk.py
pvd/anthropic/__init__.py
pvd/anthropic/wrapper.py
pvd/cli/__init__.py
pvd/cli/api.py
pvd/cli/config.py
pvd/cli/main.py
pvd/langchain/__init__.py
pvd/langchain/callbacks.py
pvd/litellm/__init__.py
pvd/litellm/wrapper.py
pvd/openai/__init__.py
pvd/openai/wrapper.py
pvd-0.1.1.dist-info/METADATA
pvd-0.1.1.dist-info/WHEEL
pvd-0.1.1.dist-info/entry_points.txt
pvd-0.1.1.dist-info/top_level.txt
pvd-0.1.1.dist-info/RECORD
