Metadata-Version: 2.4
Name: pvd
Version: 0.1.1
Summary: Paved SDK
Author: Paved (https://hipaved.com)
License: Proprietary
Requires-Python: >=3.10
Requires-Dist: click>=8.1
Requires-Dist: PyYAML>=6.0.1
Requires-Dist: requests>=2.31
Provides-Extra: cli
Provides-Extra: dev
Requires-Dist: pytest; extra == "dev"
Requires-Dist: ruff; extra == "dev"
Requires-Dist: black; extra == "dev"
Provides-Extra: openai
Requires-Dist: openai>=1.0.0; extra == "openai"
Provides-Extra: anthropic
Requires-Dist: anthropic>=0.18.0; extra == "anthropic"
Provides-Extra: litellm
Requires-Dist: litellm>=1.0.0; extra == "litellm"
Provides-Extra: langchain
Requires-Dist: langchain-core>=0.1.0; extra == "langchain"
Provides-Extra: langgraph
Requires-Dist: langgraph>=0.1.0; extra == "langgraph"
Requires-Dist: langchain-core>=0.1.0; extra == "langgraph"
Provides-Extra: langfuse
Requires-Dist: langfuse>=2.0.0; extra == "langfuse"
Provides-Extra: all
Requires-Dist: openai>=1.0.0; extra == "all"
Requires-Dist: anthropic>=0.18.0; extra == "all"
Requires-Dist: litellm>=1.0.0; extra == "all"
Requires-Dist: langchain-core>=0.1.0; extra == "all"
Requires-Dist: langgraph>=0.1.0; extra == "all"
Requires-Dist: langfuse>=2.0.0; extra == "all"
